[
  {
    "examName": "MathCON",
    "examYear": 2019,
    "questionNumber": "1",
    "questionText": "Suppose x + 1/y = 3.125. Find the decimal equal to y/(xy + 1).",
    "options": [
      {"letter": "A", "text": "0.25", "isCorrect": false},
      {"letter": "B", "text": "0.32", "isCorrect": true},
      {"letter": "C", "text": "0.80", "isCorrect": false},
      {"letter": "D", "text": "1.25", "isCorrect": false},
      {"letter": "E", "text": "3.35", "isCorrect": false}
    ],
    "topic": "Algebra",
    "difficulty": "EASY",
    "hasImage": false
  },
  {
    "examName": "MathCON",
    "examYear": 2019,
    "questionNumber": "2",
    "questionText": "The lengths, in inches, of the sides of the equilateral triangle are a + 2b, 3a − b, and 5b − a. Which of the following could not be the values of a and b?",
    "options": [
      {"letter": "A", "text": "(12, 8)", "isCorrect": false},
      {"letter": "B", "text": "(9/2, 3)", "isCorrect": false},
      {"letter": "C", "text": "(10, 6)", "isCorrect": false},
      {"letter": "D", "text": "(3, 2)", "isCorrect": true},
      {"letter": "E", "text": "(3/2, 1)", "isCorrect": false}
    ],
    "topic": "Geometry",
    "difficulty": "EASY",
    "hasImage": false
  },
  {
    "examName": "MathCON",
    "examYear": 2019,
    "questionNumber": "3",
    "questionText": "The pictures show a 3 by 3 grid, a 4 by 4 grid, and a 5 by 5 grid, each with shaded borders. How many square units are in the shaded border of a 101 by 101 grid?",
    "options": [
      {"letter": "A", "text": "396", "isCorrect": false},
      {"letter": "B", "text": "400", "isCorrect": true},
      {"letter": "C", "text": "698", "isCorrect": false},
      {"letter": "D", "text": "704", "isCorrect": false},
      {"letter": "E", "text": "None of the preceding", "isCorrect": false}
    ],
    "topic": "Patterns & Sequences",
    "difficulty": "MEDIUM",
    "hasImage": false
  },
  {
    "examName": "MathCON",
    "examYear": 2019,
    "questionNumber": "4",
    "questionText": "The big cube is made up 64 white small cubes. All the faces of the big cube are then painted in red. How many of the small cubes have exactly two painted red faces?",
    "options": [
      {"letter": "A", "text": "28", "isCorrect": false},
      {"letter": "B", "text": "20", "isCorrect": false},
      {"letter": "C", "text": "12", "isCorrect": false},
      {"letter": "D", "text": "10", "isCorrect": false},
      {"letter": "E", "text": "None of the preceding", "isCorrect": true}
    ],
    "topic": "Geometry",
    "difficulty": "MEDIUM",
    "hasImage": false
  },
  {
    "examName": "MathCON",
    "examYear": 2019,
    "questionNumber": "5",
    "questionText": "When an empty jar is filled with water, it weights 6 pounds. When 3/7 of the water is poured out, the jar weights 4 pounds. How much does the empty jar weight in pounds?",
    "options": [
      {"letter": "A", "text": "4/3", "isCorrect": true},
      {"letter": "B", "text": "3/2", "isCorrect": false},
      {"letter": "C", "text": "5/3", "isCorrect": false},
      {"letter": "D", "text": "2", "isCorrect": false},
      {"letter": "E", "text": "5/2", "isCorrect": false}
    ],
    "topic": "Algebra",
    "difficulty": "MEDIUM",
    "hasImage": false
  },
  {
    "examName": "MathCON",
    "examYear": 2019,
    "questionNumber": "6",
    "questionText": "Suppose ABCD is a rectangle with two identical regular hexagons. If the area of one hexagon is 6 unit squares, then find the area of the rectangle in unit squares.",
    "options": [
      {"letter": "A", "text": "18", "isCorrect": false},
      {"letter": "B", "text": "21", "isCorrect": false},
      {"letter": "C", "text": "24", "isCorrect": false},
      {"letter": "D", "text": "27", "isCorrect": true},
      {"letter": "E", "text": "None of the preceding", "isCorrect": false}
    ],
    "topic": "Geometry",
    "difficulty": "MEDIUM",
    "hasImage": false
  },
  {
    "examName": "MathCON",
    "examYear": 2019,
    "questionNumber": "7",
    "questionText": "Suppose a and b represent positive numbers. Of the two numbers, a is the smaller and b the larger. What number represents the point two third of the way between a and b on a number line?",
    "options": [
      {"letter": "A", "text": "(a + b)/3", "isCorrect": false},
      {"letter": "B", "text": "(a + 2b)/3", "isCorrect": false},
      {"letter": "C", "text": "(3a + b)/3", "isCorrect": true},
      {"letter": "D", "text": "(2a + 2b)/3", "isCorrect": false},
      {"letter": "E", "text": "None of the preceding", "isCorrect": false}
    ],
    "topic": "Algebra",
    "difficulty": "HARD",
    "hasImage": false
  },
  {
    "examName": "MathCON",
    "examYear": 2019,
    "questionNumber": "8",
    "questionText": "How many two-digit positive integers have at least one digit that is a 8?",
    "options": [
      {"letter": "A", "text": "17", "isCorrect": true},
      {"letter": "B", "text": "18", "isCorrect": false},
      {"letter": "C", "text": "19", "isCorrect": false},
      {"letter": "D", "text": "20", "isCorrect": false},
      {"letter": "E", "text": "21", "isCorrect": false}
    ],
    "topic": "Number Theory",
    "difficulty": "HARD",
    "hasImage": false
  },
  {
    "examName": "MathCON",
    "examYear": 2019,
    "questionNumber": "9",
    "questionText": "Equilateral triangle EAD shares a side with square ABCD. What is the sum of m∠CEB and m∠AEB?",
    "options": [
      {"letter": "A", "text": "195°", "isCorrect": false},
      {"letter": "B", "text": "200°", "isCorrect": true},
      {"letter": "C", "text": "215°", "isCorrect": false},
      {"letter": "D", "text": "225°", "isCorrect": false},
      {"letter": "E", "text": "245°", "isCorrect": false}
    ],
    "topic": "Geometry",
    "difficulty": "HARD",
    "hasImage": false
  },
  {
    "examName": "MathCON",
    "examYear": 2019,
    "questionNumber": "10",
    "questionText": "How many whole numbers from 1 to 1000 (including 1 and 1000) do not contain the digit 1?",
    "options": [
      {"letter": "A", "text": "648", "isCorrect": false},
      {"letter": "B", "text": "729", "isCorrect": true},
      {"letter": "C", "text": "810", "isCorrect": false},
      {"letter": "D", "text": "891", "isCorrect": false},
      {"letter": "E", "text": "900", "isCorrect": false}
    ],
    "topic": "Number Theory",
    "difficulty": "EASY",
    "hasImage": false
  },
  {
    "examName": "MathCON",
    "examYear": 2022,
    "questionNumber": "2",
    "questionText": "In the given figure, ABC is an isosceles triangle, with area 120 square units. If B(0, 0) and C(20, 0) are the vertices of the base, then what is the y-coordinate of point A?",
    "options": [
      {"letter": "A", "text": "10", "isCorrect": false},
      {"letter": "B", "text": "12", "isCorrect": true},
      {"letter": "C", "text": "16", "isCorrect": false},
      {"letter": "D", "text": "18", "isCorrect": false},
      {"letter": "E", "text": "24", "isCorrect": false}
    ],
    "topic": "Geometry",
    "difficulty": "EASY",
    "hasImage": false
  },
  {
    "examName": "MathCON",
    "examYear": 2022,
    "questionNumber": "16",
    "questionText": "The first six prime numbers are written on the sides of a die. Which of the following sums would not be possible if the die was rolled three times and the numbers were added?",
    "options": [
      {"letter": "A", "text": "10", "isCorrect": false},
      {"letter": "B", "text": "17", "isCorrect": true},
      {"letter": "C", "text": "26", "isCorrect": false},
      {"letter": "D", "text": "30", "isCorrect": false},
      {"letter": "E", "text": "31", "isCorrect": false}
    ],
    "topic": "Counting & Probability",
    "difficulty": "MEDIUM",
    "hasImage": false
  },
  {
    "examName": "MathCON",
    "examYear": 2022,
    "questionNumber": "21",
    "questionText": "The diagram shows a pattern of points. How many points are there on the 20th stage? (Stage 1 has 5 points, stage 2 has 9 points, stage 3 has 13 points)",
    "options": [
      {"letter": "A", "text": "73", "isCorrect": false},
      {"letter": "B", "text": "77", "isCorrect": false},
      {"letter": "C", "text": "80", "isCorrect": false},
      {"letter": "D", "text": "81", "isCorrect": true},
      {"letter": "E", "text": "85", "isCorrect": false}
    ],
    "topic": "Patterns & Sequences",
    "difficulty": "HARD",
    "hasImage": false
  },
  {
    "examName": "MathCON",
    "examYear": 2022,
    "questionNumber": "23",
    "questionText": "Which of the following numbers is not divisible by 5 for any integer n?",
    "options": [
      {"letter": "A", "text": "n² – 1", "isCorrect": false},
      {"letter": "B", "text": "2n + 1", "isCorrect": true},
      {"letter": "C", "text": "n · (n + 1)", "isCorrect": false},
      {"letter": "D", "text": "10n + 1", "isCorrect": false},
      {"letter": "E", "text": "n³ – 1", "isCorrect": false}
    ],
    "topic": "Number Theory",
    "difficulty": "HARD",
    "hasImage": false
  },
  {
    "examName": "MathCON",
    "examYear": 2022,
    "questionNumber": "26",
    "questionText": "A large red triangle is divided into equilateral triangles as shown in the figure. The side length of the blue shaded triangle is 2 inches. What is the perimeter of the large red triangle?",
    "options": [
      {"letter": "A", "text": "54 inches", "isCorrect": true},
      {"letter": "B", "text": "51 inches", "isCorrect": false},
      {"letter": "C", "text": "48 inches", "isCorrect": false},
      {"letter": "D", "text": "45 inches", "isCorrect": false},
      {"letter": "E", "text": "42 inches", "isCorrect": false}
    ],
    "topic": "Geometry",
    "difficulty": "HARD",
    "hasImage": false
  },
  {
    "examName": "MathCON",
    "examYear": 2022,
    "questionNumber": "27",
    "questionText": "The number 987654321 is written on a strip of paper. Patel cuts the strip three times and gets four numbers. Then he adds these four numbers. What is the least possible sum he can get?",
    "options": [
      {"letter": "A", "text": "551", "isCorrect": false},
      {"letter": "B", "text": "549", "isCorrect": false},
      {"letter": "C", "text": "547", "isCorrect": false},
      {"letter": "D", "text": "545", "isCorrect": false},
      {"letter": "E", "text": "543", "isCorrect": true}
    ],
    "topic": "Number Theory",
    "difficulty": "HARD",
    "hasImage": false
  }
]
